omnigpu/__init__.py
omnigpu-0.1.2.dist-info/licenses/LICENSE
omnigpu-0.1.2.dist-info/METADATA
omnigpu-0.1.2.dist-info/WHEEL
omnigpu-0.1.2.dist-info/top_level.txt
omnigpu-0.1.2.dist-info/RECORD
