Metadata-Version: 2.4
Name: omnigpu
Version: 0.1.2
Summary: Placeholder package while OmniGPU is under redevelopment
Author-email: "Badel L. Mbanga" <badel@eigenbasis.ai>
License: MIT License
Project-URL: Homepage, https://github.com/badelmbanga/omnigpu
Project-URL: Source, https://github.com/badelmbanga/omnigpu
Project-URL: Bug Tracker, https://github.com/badelmbanga/omnigpu/issues
Keywords: placeholder,omnigpu
Classifier: Development Status :: 1 - Planning
Classifier: Intended Audience :: Developers
Classifier: License :: OSI Approved :: MIT License
Classifier: Programming Language :: Python
Classifier: Programming Language :: Python :: 3
Classifier: Topic :: Software Development :: Build Tools
Requires-Python: >=3.8
License-File: LICENSE
Dynamic: license-file
